{
  "first_names": {
    "male": {
      "very_common": [
        "Muhammad",
        "Ahmed",
        "Ali",
        "Hassan",
        "Usman",
        "Hamza",
        "Bilal",
        "Omar",
        "Imran",
        "Shahid",
        "Khalid",
        "Tariq",
        "Asif",
        "Kamran",
        "Faisal",
        "Aamir",
        "Waseem",
        "Rizwan",
        "Nabeel",
        "Zubair"
      ],
      "common": [
        "Adnan",
        "Arshad",
        "Sajid",
        "Kashif",
        "Irfan",
        "Jehangir",
        "Naveed",
        "Saad",
        "Waqar",
        "Zahid",
        "Shoaib",
        "Fahad",
        "Junaid",
        "Nadeem",
        "Rehan",
        "Sohail",
        "Tahir",
        "Yasir",
        "Zeeshan",
        "Atif",
        "Bashir",
        "Dawood",
        "Ehsan",
        "Farhan",
        "Ghulam",
        "Habib",
        "Ijaz",
        "Javed",
        "Liaqat",
        "Mushtaq",
        "Nasir",
        "Qamar",
        "Rafiq",
        "Shafiq",
        "Umar",
        "Wajid",
        "Yousuf",
        "Abbas",
        "Haider",
        "Saeed"
      ],
      "uncommon": [
        "Asghar",
        "Babar",
        "Daniyal",
        "Fayyaz",
        "Gulzar",
        "Hamid",
        "Iftikhar",
        "Kamal",
        "Latif",
        "Manzoor",
        "Nisar",
        "Pervaiz",
        "Qasim",
        "Rauf",
        "Sarfraz",
        "Tanveer",
        "Wahab",
        "Zaheer",
        "Akhtar",
        "Basharat",
        "Dilshad",
        "Feroz",
        "Hanif",
        "Israr",
        "Jamil",
        "Khurram",
        "Mazhar",
        "Naeem",
        "Raza",
        "Shabbir",
        "Umer",
        "Wali",
        "Zafar",
        "Anwar",
        "Aziz",
        "Farooq",
        "Ikram",
        "Majid",
        "Noman",
        "Sajjad",
        "Taufeeq",
        "Waheed",
        "Younus",
        "Zia",
        "Afzal",
        "Mudassar",
        "Shakeel",
        "Aqeel",
        "Sultan",
        "Mehmood",
        "Munir",
        "Raheel",
        "Sikandar",
        "Talha",
        "Umair",
        "Waleed",
        "Mubashir",
        "Kamil",
        "Haris"
      ],
      "rare": [
        "Akbar",
        "Baqir",
        "Changez",
        "Dilawar",
        "Fakhar",
        "Gohar",
        "Hashim",
        "Inayat",
        "Jaffer",
        "Khizar",
        "Luqman",
        "Mehboob",
        "Nouman",
        "Obaid",
        "Parvez",
        "Qadir",
        "Rasheed",
        "Sabir",
        "Taimur",
        "Ubaid",
        "Vaqar",
        "Yasin",
        "Zeenat",
        "Arif",
        "Barkat",
        "Danish",
        "Fazal",
        "Ghaus",
        "Hayat",
        "Ishtiaq",
        "Jalil",
        "Khawar",
        "Maqsood",
        "Nawaz",
        "Qayyum",
        "Riaz",
        "Shahbaz",
        "Tufail",
        "Uzair",
        "Waqas",
        "Zaman",
        "Aftab",
        "Burhan",
        "Dildar",
        "Fiaz",
        "Ghaffar",
        "Hussain",
        "Inam",
        "Kifayat",
        "Liaquat",
        "Mujahid",
        "Naqvi",
        "Shaukat",
        "Suliman",
        "Tahsin",
        "Wajahat",
        "Zulfiqar",
        "Amir",
        "Baber",
        "Durrani",
        "Fasih",
        "Gulshan",
        "Hikmat",
        "Ibad",
        "Jawad",
        "Lakhani",
        "Mirza",
        "Noor",
        "Pirzada",
        "Roshan",
        "Sarwar",
        "Tughlaq",
        "Umayr",
        "Zaid",
        "Azhar",
        "Basit",
        "Ehsaan",
        "Fareed",
        "Haseeb"
      ]
    },
    "female": {
      "very_common": [
        "Fatima",
        "Ayesha",
        "Sana",
        "Maryam",
        "Hira",
        "Zainab",
        "Amna",
        "Rabia",
        "Nadia",
        "Maria",
        "Khadija",
        "Saima",
        "Saba",
        "Huma",
        "Farah",
        "Noor",
        "Samina",
        "Bushra",
        "Uzma",
        "Asma"
      ],
      "common": [
        "Aisha",
        "Sidra",
        "Madiha",
        "Nimra",
        "Aqsa",
        "Laiba",
        "Mehwish",
        "Naila",
        "Rida",
        "Sumera",
        "Tahira",
        "Yasmin",
        "Zubaida",
        "Afshan",
        "Bano",
        "Durr-e-Nayab",
        "Farida",
        "Ghazala",
        "Humaira",
        "Iffat",
        "Jamila",
        "Kanwal",
        "Lubna",
        "Muneeba",
        "Nighat",
        "Parveen",
        "Qurat",
        "Riffat",
        "Shazia",
        "Tasneem",
        "Wardah",
        "Zara",
        "Amber",
        "Benazir",
        "Deeba",
        "Farzana",
        "Gulnaz",
        "Irum",
        "Javeria",
        "Khalida"
      ],
      "uncommon": [
        "Aliya",
        "Bilquis",
        "Chanda",
        "Dilshad",
        "Fauzia",
        "Gulshan",
        "Hajra",
        "Ishrat",
        "Kiran",
        "Liaqat",
        "Meher",
        "Naheed",
        "Qamar",
        "Rubina",
        "Sajida",
        "Tabassum",
        "Wajeeha",
        "Zahida",
        "Anjum",
        "Begum",
        "Durdana",
        "Fakhra",
        "Gul",
        "Haleema",
        "Imrana",
        "Kousar",
        "Misbah",
        "Nasreen",
        "Rukhsana",
        "Shahida",
        "Tanveer",
        "Waheeda",
        "Zohra",
        "Anila",
        "Batool",
        "Fouzia",
        "Habiba",
        "Kubra",
        "Malika",
        "Noreen",
        "Rakhshanda",
        "Sakina",
        "Talat",
        "Yasira",
        "Zenith",
        "Alia",
        "Bahar",
        "Fehmida",
        "Ghazal",
        "Ifra",
        "Layla",
        "Mahira",
        "Nargis",
        "Raheela",
        "Shamim",
        "Tayyaba",
        "Urooj",
        "Zubi",
        "Areeba"
      ],
      "rare": [
        "Almas",
        "Basma",
        "Channar",
        "Durri",
        "Faryal",
        "Gohar",
        "Husna",
        "Ismat",
        "Jameela",
        "Kausar",
        "Laaleen",
        "Mashal",
        "Najma",
        "Roohi",
        "Saadia",
        "Tohfa",
        "Warda",
        "Zarqa",
        "Afia",
        "Barirah",
        "Daleel",
        "Fateh",
        "Ghania",
        "Hoor",
        "Iqra",
        "Jannat",
        "Khansa",
        "Mahnoor",
        "Nayyab",
        "Ramsha",
        "Sumaira",
        "Tehreem",
        "Unza",
        "Zoya",
        "Alishba",
        "Bismah",
        "Eiman",
        "Fiza",
        "Hafsa",
        "Inaya",
        "Kinza",
        "Minal",
        "Neha",
        "Roshni",
        "Sundas",
        "Tamkeen",
        "Uroosa",
        "Zareen",
        "Areesha",
        "Eshal",
        "Emaan",
        "Hoorain",
        "Sadia",
        "Shifa",
        "Tuba",
        "Mishaal",
        "Hareem",
        "Momina",
        "Ruqayya",
        "Samra",
        "Anam",
        "Humna",
        "Minahil",
        "Nawal",
        "Sawera",
        "Erum",
        "Faiza",
        "Khizra",
        "Maira",
        "Nimrah",
        "Afreen",
        "Dua",
        "Hamna",
        "Jaweria",
        "Mariyam",
        "Nashit",
        "Rameen",
        "Areej",
        "Eman"
      ]
    },
    "neutral": {
      "very_common": [
        "Noor"
      ],
      "common": [
        "Iman",
        "Dana"
      ],
      "uncommon": [
        "Dil",
        "Mehak",
        "Roshan"
      ],
      "rare": [
        "Sarmad",
        "Tayyab",
        "Shahab",
        "Shua"
      ]
    }
  },
  "last_names": {
    "very_common": [
      "Khan",
      "Ahmed",
      "Ali",
      "Hussain",
      "Malik",
      "Sheikh",
      "Butt",
      "Chaudhry",
      "Iqbal",
      "Siddiqui",
      "Qureshi",
      "Akhtar",
      "Raza",
      "Shah",
      "Hashmi",
      "Rizvi",
      "Aslam",
      "Lodhi",
      "Mirza",
      "Baig"
    ],
    "common": [
      "Abbasi",
      "Bhatti",
      "Dar",
      "Farooqi",
      "Gilani",
      "Javed",
      "Kazmi",
      "Mughal",
      "Naqvi",
      "Rajput",
      "Saeed",
      "Tahir",
      "Usmani",
      "Zafar",
      "Ansari",
      "Baloch",
      "Durrani",
      "Ghori",
      "Hayat",
      "Jilani",
      "Khattak",
      "Niazi",
      "Pasha",
      "Rana",
      "Sharif",
      "Wattoo",
      "Zaidi",
      "Arshad",
      "Bajwa",
      "Cheema",
      "Gondal",
      "Haider",
      "Khawaja",
      "Mahmood",
      "Noon",
      "Pirzada",
      "Sarwar",
      "Tarar",
      "Warsi",
      "Yousaf"
    ],
    "uncommon": [
      "Afridi",
      "Bangash",
      "Dawar",
      "Ghauri",
      "Hotiana",
      "Jalali",
      "Kirmani",
      "Langrial",
      "Marwat",
      "Naushahi",
      "Paracha",
      "Raisani",
      "Sethi",
      "Tiwana",
      "Waraich",
      "Yusufzai",
      "Awan",
      "Bokhari",
      "Dogar",
      "Gardezi",
      "Haroon",
      "Junejo",
      "Khuhro",
      "Leghari",
      "Mengal",
      "Orakzai",
      "Qazi",
      "Swati",
      "Talpur",
      "Zardari",
      "Achakzai",
      "Bugti",
      "Daultana",
      "Gujjar",
      "Hazarvi",
      "Jhagra",
      "Khar",
      "Mandokhel",
      "Nakhai",
      "Palijo",
      "Rind",
      "Soomro",
      "Tunio",
      "Umrani",
      "Wazir",
      "Yousafzai",
      "Achekzai",
      "Brohi",
      "Chandio",
      "Gabol",
      "Jamali",
      "Khoso",
      "Lund",
      "Magsi",
      "Narejo",
      "Pitafi",
      "Samoo",
      "Thaheem",
      "Wassan",
      "Zehri"
    ],
    "rare": [
      "Arain",
      "Bhurgri",
      "Dahri",
      "Gabool",
      "Hisbani",
      "Joyo",
      "Kaleri",
      "Lashari",
      "Mahar",
      "Notezai",
      "Panhwar",
      "Rajar",
      "Shaikh",
      "Tamachi",
      "Unnar",
      "Veesar",
      "Zahri",
      "Abro",
      "Bhayo",
      "Chachar",
      "Dero",
      "Gaad",
      "Halipoto",
      "Jakhrani",
      "Khokhar",
      "Laghari",
      "Mahesar",
      "Naich",
      "Phul",
      "Rahpoto",
      "Siyal",
      "Talani",
      "Ujan",
      "Wagan",
      "Yarkhan",
      "Agha",
      "Baladi",
      "Charan",
      "Dahani",
      "Gadhi",
      "Hingorjo",
      "Jamote",
      "Kalhoro",
      "Lakho",
      "Mangi",
      "Noonari",
      "Pahore",
      "Rajpar",
      "Sarki",
      "Thebo",
      "Veho",
      "Wasan",
      "Zangejo",
      "Bhanbhro",
      "Chanar",
      "Detho",
      "Ghoto",
      "Hakro",
      "Jatoi",
      "Keerio",
      "Lakhmir",
      "Mallah",
      "Nizamani",
      "Panhyar",
      "Solangi",
      "Udero",
      "Waseer",
      "Zangishahi",
      "Abrejo",
      "Barfat",
      "Chandrani",
      "Dayo",
      "Gopang",
      "Halepoto",
      "Juno",
      "Katpar",
      "Lohar",
      "Meghwar",
      "Otho",
      "Rahu",
      "Shar",
      "Veengas",
      "Zardani",
      "Abidi",
      "Bukhari",
      "Gardez",
      "Habib"
    ]
  },
  "name_formats": [
    "{first_name} {last_name}"
  ],
  "prefixes": {
    "male": [
      "Mr.",
      "Dr."
    ],
    "female": [
      "Mrs.",
      "Ms.",
      "Dr."
    ],
    "neutral": [
      "Dr."
    ]
  },
  "suffixes": []
}
